dtrack_mcp_server/__init__.py
dtrack_mcp_server/dtrack_client.py
dtrack_mcp_server/server.py
mareana_dtrack_mcp_server-0.1.0.dist-info/METADATA
mareana_dtrack_mcp_server-0.1.0.dist-info/WHEEL
mareana_dtrack_mcp_server-0.1.0.dist-info/entry_points.txt
mareana_dtrack_mcp_server-0.1.0.dist-info/licenses/LICENSE
mareana_dtrack_mcp_server-0.1.0.dist-info/RECORD
