Metadata-Version: 2.4
Name: mareana-dtrack-mcp-server
Version: 0.1.0
Summary: DependencyTrack MCP Server for vulnerability assessment in CI/CD pipelines
Project-URL: Homepage, https://github.com/mareana/dtrack-mcp-server
Project-URL: Repository, https://github.com/mareana/dtrack-mcp-server
Project-URL: Documentation, https://github.com/mareana/dtrack-mcp-server/blob/main/README.md
Project-URL: Issues, https://github.com/mareana/dtrack-mcp-server/issues
Author-email: Shashanka G <shashanka.g@mareana.com>
License: MIT
License-File: LICENSE
Keywords: ci-cd,dependencytrack,mcp,security,vulnerability
Classifier: Development Status :: 4 - Beta
Classifier: Intended Audience :: Developers
Classifier: License :: OSI Approved :: MIT License
Classifier: Programming Language :: Python :: 3
Classifier: Programming Language :: Python :: 3.8
Classifier: Programming Language :: Python :: 3.9
Classifier: Programming Language :: Python :: 3.10
Classifier: Programming Language :: Python :: 3.11
Classifier: Programming Language :: Python :: 3.12
Classifier: Topic :: Security
Classifier: Topic :: Software Development :: Quality Assurance
Requires-Python: >=3.8
Requires-Dist: mcp>=1.0.0
Requires-Dist: pydantic>=2.0.0
Requires-Dist: requests>=2.31.0
Provides-Extra: dev
Requires-Dist: black>=23.0.0; extra == 'dev'
Requires-Dist: build>=0.10.0; extra == 'dev'
Requires-Dist: mypy>=1.0.0; extra == 'dev'
Requires-Dist: pytest>=7.0.0; extra == 'dev'
Requires-Dist: twine>=4.0.0; extra == 'dev'
